MANIFEST.in
README.md
setup.py
bottle_memcache_decorator/__init__.py
bottle_memcache_decorator/bottle_memcache_decorator.py
bottle_memcache_decorator.egg-info/PKG-INFO
bottle_memcache_decorator.egg-info/SOURCES.txt
bottle_memcache_decorator.egg-info/dependency_links.txt
bottle_memcache_decorator.egg-info/requires.txt
bottle_memcache_decorator.egg-info/top_level.txt