Metadata-Version: 1.1
Name: bottle-memcache-decorator
Version: 0.0.1
Summary: Adds a memcache decorator in your Bottle application.         It automatically stores the route result to memcache for routes         where the bottle-memcache plugin is enabled.
Home-page: http://github.com/ziogaschr/bottle-memcache-decorator
Author: Chris Ziogas
Author-email: ziogas_chr@hotmail.com
License: MIT
Download-URL: https://github.com/ziogaschr/bottle-memcache-decorator/tarball/v0.0.1#egg=ziogaschr/bottle-memcache-decorator-0.0.1
Keywords: Bottle Plugin Memcache Decorator
Platform: any
Classifier: Development Status :: 3 - Alpha
Classifier: Environment :: Plugins
Classifier: Framework :: Bottle
Classifier: License :: OSI Approved :: MIT License
Classifier: Intended Audience :: Developers
Classifier: Operating System :: OS Independent
Classifier: Programming Language :: Python
Classifier: Topic :: Internet :: WWW/HTTP :: Dynamic Content
Classifier: Topic :: Software Development :: Libraries :: Python Modules
